podcast_recommendation/__init__.py
podcast_recommendation/algorithm.py
podcast_recommendation/data/categories_sample.csv
podcast_recommendation/data/podcast_sample_title.csv
podcast_recommendation/data/ratings_sample.csv
podcast_recommendation/data/x_train.csv
podcast_recommendation/data/y_train.csv
podcast_recommendation-0.1.8.dist-info/LICENSE
podcast_recommendation-0.1.8.dist-info/METADATA
podcast_recommendation-0.1.8.dist-info/WHEEL
podcast_recommendation-0.1.8.dist-info/top_level.txt
podcast_recommendation-0.1.8.dist-info/RECORD
